README.md
setup.py
scrapy_ajax_utils/__init__.py
scrapy_ajax_utils/splash.py
scrapy_ajax_utils/utils.py
scrapy_ajax_utils.egg-info/PKG-INFO
scrapy_ajax_utils.egg-info/SOURCES.txt
scrapy_ajax_utils.egg-info/dependency_links.txt
scrapy_ajax_utils.egg-info/requires.txt
scrapy_ajax_utils.egg-info/top_level.txt
scrapy_ajax_utils/selenium/__init__.py
scrapy_ajax_utils/selenium/browser.py
scrapy_ajax_utils/selenium/middleware.py
scrapy_ajax_utils/selenium/request.py