Metadata-Version: 2.1
Name: scrapy-ajax-utils
Version: 0.1272
Summary: ajax utils for scrapy.
Home-page: https://github.com/financialfly/scrapy_ajax_utils
Author: financial
Author-email: 1012593988@qq.com
Maintainer: financial
Maintainer-email: 1012593988@qq.com
License: BSD License
Platform: all
Classifier: Development Status :: 4 - Beta
Classifier: Operating System :: OS Independent
Classifier: Intended Audience :: Developers
Classifier: License :: OSI Approved :: BSD License
Classifier: Programming Language :: Python
Classifier: Programming Language :: Python :: Implementation
Classifier: Programming Language :: Python :: 3
Classifier: Programming Language :: Python :: 3.4
Classifier: Programming Language :: Python :: 3.5
Classifier: Programming Language :: Python :: 3.6
Classifier: Programming Language :: Python :: 3.7
Classifier: Topic :: Software Development :: Libraries
